ptb_ext/__init__.py
ptb_ext/conversation_ext.py
ptb_ext/lib.py
ptb_ext/logging_ext.py
ptb_ext/types.py
ptb_ext-0.1.3.dist-info/METADATA
ptb_ext-0.1.3.dist-info/WHEEL
ptb_ext-0.1.3.dist-info/RECORD
